whois/__init__.py
whois/cache/__init__.py
whois/cache/dbmCache.py
whois/cache/dummyCache.py
whois/cache/redisCache.py
whois/cache/simpleCacheBase.py
whois/cache/simpleCacheWithFile.py
whois/context/__init__.py
whois/context/dataContext.py
whois/context/parameterContext.py
whois/data/public_suffix_list.dat
whois/domain.py
whois/doWhoisCommand.py
whois/exceptions.py
whois/handleDateStrings.py
whois/helpers.py
whois/lastWhois.py
whois/main.py
whois/parser.py
whois/processWhoisDomainRequest.py
whois/strings/__init__.py
whois/strings/ignoreStrings.py
whois/strings/noneStrings.py
whois/strings/quotaStrings.py
whois/time_zones.py
whois/tldDb/__init__.py
whois/tldDb/finders.py
whois/tldDb/groupers.py
whois/tldDb/tld_regexpr.py
whois/tldInfo.py
whois/version.py
whois/whois.py
whois/whoisCliInterface.py
whois/whoisParser.py
whoisenriched-0.1.0.dist-info/METADATA
whoisenriched-0.1.0.dist-info/WHEEL
whoisenriched-0.1.0.dist-info/RECORD
