Metadata-Version: 2.1
Name: whoisenriched
Version: 0.1.0
Summary: This project builded for enrichment of WhoIs Library's Queries
Author: Efe Gençalioğlu
Requires-Python: >=3.11,<4.0
Classifier: Programming Language :: Python :: 3
Classifier: Programming Language :: Python :: 3.11
